.gitignore
AUTHORS
LICENSE
README.md
setup.py
wallaby/__init__.py
wallaby/apps/__init__.py
wallaby/apps/inspector/UI_mainWindow.py
wallaby/apps/inspector/__init__.py
wallaby/apps/inspector/app.qrc
wallaby/apps/inspector/app_rc.py
wallaby/apps/inspector/mainWindow.py
wallaby/apps/inspector/mainWindow.ui
wallaby/apps/inspector/couchapp/.couchappignore
wallaby/apps/inspector/couchapp/.couchapprc
wallaby/apps/inspector/couchapp/_id
wallaby/apps/inspector/couchapp/_docs/WallabyApp.json
wallaby/apps/inspector/couchapp/filters/articles.js
wallaby/apps/inspector/couchapp/views/example/map.js
wallaby/apps/inspector/es/example.json
wallaby/apps/inspector/images/__empty__
wallaby/apps/inspector/isheet/__init__.py
wallaby/apps/inspector/peer/__init__.py
wallaby/apps/inspector/plugins/__init__.py
wallaby/apps/inspector/prefs/__init__.py
wallaby/apps/inspector/rooms/__config__.py
wallaby/apps/inspector/rooms/__init__.py
wallaby/apps/inspector/widgets/__init__.py
wallaby_app_inspector.egg-info/PKG-INFO
wallaby_app_inspector.egg-info/SOURCES.txt
wallaby_app_inspector.egg-info/dependency_links.txt
wallaby_app_inspector.egg-info/requires.txt
wallaby_app_inspector.egg-info/top_level.txt